{
  "seriesID": "LAUCN221150000000005",
  "data": [
    {
      "year": "2025",
      "period": "M12",
      "periodName": "December",
      "latest": "true",
      "value": "15794",
      "footnotes": [
        {
          "code": "P",
          "text": "Preliminary."
        }
      ]
    },
    {
      "year": "2025",
      "period": "M11",
      "periodName": "November",
      "value": "16040",
      "footnotes": [
        {}
      ]
    },
    {
      "year": "2025",
      "period": "M10",
      "periodName": "October",
      "value": "-",
      "footnotes": [
        {
          "code": "X",
          "text": "Data unavailable due to the 2025 lapse in appropriations."
        }
      ]
    },
    {
      "year": "2025",
      "period": "M09",
      "periodName": "September",
      "value": "15924",
      "footnotes": [
        {}
      ]
    },
    {
      "year": "2025",
      "period": "M08",
      "periodName": "August",
      "value": "15868",
      "footnotes": [
        {}
      ]
    },
    {
      "year": "2025",
      "period": "M07",
      "periodName": "July",
      "value": "16043",
      "footnotes": [
        {}
      ]
    },
    {
      "year": "2025",
      "period": "M06",
      "periodName": "June",
      "value": "16204",
      "footnotes": [
        {}
      ]
    },
    {
      "year": "2025",
      "period": "M05",
      "periodName": "May",
      "value": "16006",
      "footnotes": [
        {}
      ]
    },
    {
      "year": "2025",
      "period": "M04",
      "periodName": "April",
      "value": "16121",
      "footnotes": [
        {}
      ]
    },
    {
      "year": "2025",
      "period": "M03",
      "periodName": "March",
      "value": "16133",
      "footnotes": [
        {}
      ]
    },
    {
      "year": "2025",
      "period": "M02",
      "periodName": "February",
      "value": "15928",
      "footnotes": [
        {}
      ]
    },
    {
      "year": "2025",
      "period": "M01",
      "periodName": "January",
      "value": "15887",
      "footnotes": [
        {}
      ]
    },
    {
      "year": "2024",
      "period": "M12",
      "periodName": "December",
      "value": "15861",
      "footnotes": [
        {}
      ]
    },
    {
      "year": "2024",
      "period": "M11",
      "periodName": "November",
      "value": "16082",
      "footnotes": [
        {}
      ]
    },
    {
      "year": "2024",
      "period": "M10",
      "periodName": "October",
      "value": "16147",
      "footnotes": [
        {}
      ]
    },
    {
      "year": "2024",
      "period": "M09",
      "periodName": "September",
      "value": "16439",
      "footnotes": [
        {}
      ]
    },
    {
      "year": "2024",
      "period": "M08",
      "periodName": "August",
      "value": "16250",
      "footnotes": [
        {}
      ]
    },
    {
      "year": "2024",
      "period": "M07",
      "periodName": "July",
      "value": "16627",
      "footnotes": [
        {}
      ]
    },
    {
      "year": "2024",
      "period": "M06",
      "periodName": "June",
      "value": "16725",
      "footnotes": [
        {}
      ]
    },
    {
      "year": "2024",
      "period": "M05",
      "periodName": "May",
      "value": "16161",
      "footnotes": [
        {}
      ]
    },
    {
      "year": "2024",
      "period": "M04",
      "periodName": "April",
      "value": "16419",
      "footnotes": [
        {}
      ]
    },
    {
      "year": "2024",
      "period": "M03",
      "periodName": "March",
      "value": "16418",
      "footnotes": [
        {}
      ]
    },
    {
      "year": "2024",
      "period": "M02",
      "periodName": "February",
      "value": "15974",
      "footnotes": [
        {}
      ]
    },
    {
      "year": "2024",
      "period": "M01",
      "periodName": "January",
      "value": "16083",
      "footnotes": [
        {}
      ]
    },
    {
      "year": "2023",
      "period": "M12",
      "periodName": "December",
      "value": "16000",
      "footnotes": [
        {}
      ]
    },
    {
      "year": "2023",
      "period": "M11",
      "periodName": "November",
      "value": "16063",
      "footnotes": [
        {}
      ]
    },
    {
      "year": "2023",
      "period": "M10",
      "periodName": "October",
      "value": "16534",
      "footnotes": [
        {}
      ]
    },
    {
      "year": "2023",
      "period": "M09",
      "periodName": "September",
      "value": "16748",
      "footnotes": [
        {}
      ]
    },
    {
      "year": "2023",
      "period": "M08",
      "periodName": "August",
      "value": "16654",
      "footnotes": [
        {}
      ]
    },
    {
      "year": "2023",
      "period": "M07",
      "periodName": "July",
      "value": "17081",
      "footnotes": [
        {}
      ]
    },
    {
      "year": "2023",
      "period": "M06",
      "periodName": "June",
      "value": "17336",
      "footnotes": [
        {}
      ]
    },
    {
      "year": "2023",
      "period": "M05",
      "periodName": "May",
      "value": "16729",
      "footnotes": [
        {}
      ]
    },
    {
      "year": "2023",
      "period": "M04",
      "periodName": "April",
      "value": "17118",
      "footnotes": [
        {}
      ]
    },
    {
      "year": "2023",
      "period": "M03",
      "periodName": "March",
      "value": "16766",
      "footnotes": [
        {}
      ]
    },
    {
      "year": "2023",
      "period": "M02",
      "periodName": "February",
      "value": "16928",
      "footnotes": [
        {}
      ]
    },
    {
      "year": "2023",
      "period": "M01",
      "periodName": "January",
      "value": "16837",
      "footnotes": [
        {}
      ]
    },
    {
      "year": "2022",
      "period": "M12",
      "periodName": "December",
      "value": "16434",
      "footnotes": [
        {}
      ]
    },
    {
      "year": "2022",
      "period": "M11",
      "periodName": "November",
      "value": "16512",
      "footnotes": [
        {}
      ]
    },
    {
      "year": "2022",
      "period": "M10",
      "periodName": "October",
      "value": "16257",
      "footnotes": [
        {}
      ]
    },
    {
      "year": "2022",
      "period": "M09",
      "periodName": "September",
      "value": "16723",
      "footnotes": [
        {}
      ]
    },
    {
      "year": "2022",
      "period": "M08",
      "periodName": "August",
      "value": "16646",
      "footnotes": [
        {}
      ]
    },
    {
      "year": "2022",
      "period": "M07",
      "periodName": "July",
      "value": "17043",
      "footnotes": [
        {}
      ]
    },
    {
      "year": "2022",
      "period": "M06",
      "periodName": "June",
      "value": "16594",
      "footnotes": [
        {}
      ]
    },
    {
      "year": "2022",
      "period": "M05",
      "periodName": "May",
      "value": "16487",
      "footnotes": [
        {}
      ]
    },
    {
      "year": "2022",
      "period": "M04",
      "periodName": "April",
      "value": "16649",
      "footnotes": [
        {}
      ]
    },
    {
      "year": "2022",
      "period": "M03",
      "periodName": "March",
      "value": "16189",
      "footnotes": [
        {}
      ]
    },
    {
      "year": "2022",
      "period": "M02",
      "periodName": "February",
      "value": "16490",
      "footnotes": [
        {}
      ]
    },
    {
      "year": "2022",
      "period": "M01",
      "periodName": "January",
      "value": "16287",
      "footnotes": [
        {}
      ]
    },
    {
      "year": "2021",
      "period": "M12",
      "periodName": "December",
      "value": "15903",
      "footnotes": [
        {}
      ]
    },
    {
      "year": "2021",
      "period": "M11",
      "periodName": "November",
      "value": "16153",
      "footnotes": [
        {}
      ]
    },
    {
      "year": "2021",
      "period": "M10",
      "periodName": "October",
      "value": "16075",
      "footnotes": [
        {}
      ]
    },
    {
      "year": "2021",
      "period": "M09",
      "periodName": "September",
      "value": "16733",
      "footnotes": [
        {}
      ]
    },
    {
      "year": "2021",
      "period": "M08",
      "periodName": "August",
      "value": "16240",
      "footnotes": [
        {}
      ]
    },
    {
      "year": "2021",
      "period": "M07",
      "periodName": "July",
      "value": "16314",
      "footnotes": [
        {}
      ]
    },
    {
      "year": "2021",
      "period": "M06",
      "periodName": "June",
      "value": "16297",
      "footnotes": [
        {}
      ]
    },
    {
      "year": "2021",
      "period": "M05",
      "periodName": "May",
      "value": "15719",
      "footnotes": [
        {}
      ]
    },
    {
      "year": "2021",
      "period": "M04",
      "periodName": "April",
      "value": "16272",
      "footnotes": [
        {}
      ]
    },
    {
      "year": "2021",
      "period": "M03",
      "periodName": "March",
      "value": "16143",
      "footnotes": [
        {}
      ]
    },
    {
      "year": "2021",
      "period": "M02",
      "periodName": "February",
      "value": "16011",
      "footnotes": [
        {}
      ]
    },
    {
      "year": "2021",
      "period": "M01",
      "periodName": "January",
      "value": "15474",
      "footnotes": [
        {}
      ]
    }
  ]
}