{
  "seriesID": "LAUCN280710000000005",
  "data": [
    {
      "year": "2025",
      "period": "M12",
      "periodName": "December",
      "latest": "true",
      "value": "28852",
      "footnotes": [
        {
          "code": "P",
          "text": "Preliminary."
        }
      ]
    },
    {
      "year": "2025",
      "period": "M11",
      "periodName": "November",
      "value": "29127",
      "footnotes": [
        {}
      ]
    },
    {
      "year": "2025",
      "period": "M10",
      "periodName": "October",
      "value": "-",
      "footnotes": [
        {
          "code": "X",
          "text": "Data unavailable due to the 2025 lapse in appropriations."
        }
      ]
    },
    {
      "year": "2025",
      "period": "M09",
      "periodName": "September",
      "value": "29221",
      "footnotes": [
        {}
      ]
    },
    {
      "year": "2025",
      "period": "M08",
      "periodName": "August",
      "value": "27876",
      "footnotes": [
        {}
      ]
    },
    {
      "year": "2025",
      "period": "M07",
      "periodName": "July",
      "value": "27577",
      "footnotes": [
        {}
      ]
    },
    {
      "year": "2025",
      "period": "M06",
      "periodName": "June",
      "value": "27993",
      "footnotes": [
        {}
      ]
    },
    {
      "year": "2025",
      "period": "M05",
      "periodName": "May",
      "value": "28567",
      "footnotes": [
        {}
      ]
    },
    {
      "year": "2025",
      "period": "M04",
      "periodName": "April",
      "value": "29235",
      "footnotes": [
        {}
      ]
    },
    {
      "year": "2025",
      "period": "M03",
      "periodName": "March",
      "value": "28872",
      "footnotes": [
        {}
      ]
    },
    {
      "year": "2025",
      "period": "M02",
      "periodName": "February",
      "value": "28615",
      "footnotes": [
        {}
      ]
    },
    {
      "year": "2025",
      "period": "M01",
      "periodName": "January",
      "value": "27606",
      "footnotes": [
        {}
      ]
    },
    {
      "year": "2024",
      "period": "M12",
      "periodName": "December",
      "value": "28131",
      "footnotes": [
        {}
      ]
    },
    {
      "year": "2024",
      "period": "M11",
      "periodName": "November",
      "value": "28824",
      "footnotes": [
        {}
      ]
    },
    {
      "year": "2024",
      "period": "M10",
      "periodName": "October",
      "value": "28737",
      "footnotes": [
        {}
      ]
    },
    {
      "year": "2024",
      "period": "M09",
      "periodName": "September",
      "value": "28586",
      "footnotes": [
        {}
      ]
    },
    {
      "year": "2024",
      "period": "M08",
      "periodName": "August",
      "value": "26969",
      "footnotes": [
        {}
      ]
    },
    {
      "year": "2024",
      "period": "M07",
      "periodName": "July",
      "value": "26180",
      "footnotes": [
        {}
      ]
    },
    {
      "year": "2024",
      "period": "M06",
      "periodName": "June",
      "value": "26584",
      "footnotes": [
        {}
      ]
    },
    {
      "year": "2024",
      "period": "M05",
      "periodName": "May",
      "value": "27429",
      "footnotes": [
        {}
      ]
    },
    {
      "year": "2024",
      "period": "M04",
      "periodName": "April",
      "value": "28064",
      "footnotes": [
        {}
      ]
    },
    {
      "year": "2024",
      "period": "M03",
      "periodName": "March",
      "value": "27502",
      "footnotes": [
        {}
      ]
    },
    {
      "year": "2024",
      "period": "M02",
      "periodName": "February",
      "value": "27383",
      "footnotes": [
        {}
      ]
    },
    {
      "year": "2024",
      "period": "M01",
      "periodName": "January",
      "value": "25711",
      "footnotes": [
        {}
      ]
    },
    {
      "year": "2023",
      "period": "M12",
      "periodName": "December",
      "value": "26356",
      "footnotes": [
        {}
      ]
    },
    {
      "year": "2023",
      "period": "M11",
      "periodName": "November",
      "value": "27741",
      "footnotes": [
        {}
      ]
    },
    {
      "year": "2023",
      "period": "M10",
      "periodName": "October",
      "value": "27643",
      "footnotes": [
        {}
      ]
    },
    {
      "year": "2023",
      "period": "M09",
      "periodName": "September",
      "value": "27711",
      "footnotes": [
        {}
      ]
    },
    {
      "year": "2023",
      "period": "M08",
      "periodName": "August",
      "value": "26278",
      "footnotes": [
        {}
      ]
    },
    {
      "year": "2023",
      "period": "M07",
      "periodName": "July",
      "value": "25131",
      "footnotes": [
        {}
      ]
    },
    {
      "year": "2023",
      "period": "M06",
      "periodName": "June",
      "value": "25657",
      "footnotes": [
        {}
      ]
    },
    {
      "year": "2023",
      "period": "M05",
      "periodName": "May",
      "value": "26589",
      "footnotes": [
        {}
      ]
    },
    {
      "year": "2023",
      "period": "M04",
      "periodName": "April",
      "value": "27293",
      "footnotes": [
        {}
      ]
    },
    {
      "year": "2023",
      "period": "M03",
      "periodName": "March",
      "value": "26959",
      "footnotes": [
        {}
      ]
    },
    {
      "year": "2023",
      "period": "M02",
      "periodName": "February",
      "value": "26796",
      "footnotes": [
        {}
      ]
    },
    {
      "year": "2023",
      "period": "M01",
      "periodName": "January",
      "value": "25613",
      "footnotes": [
        {}
      ]
    },
    {
      "year": "2022",
      "period": "M12",
      "periodName": "December",
      "value": "26100",
      "footnotes": [
        {}
      ]
    },
    {
      "year": "2022",
      "period": "M11",
      "periodName": "November",
      "value": "27047",
      "footnotes": [
        {}
      ]
    },
    {
      "year": "2022",
      "period": "M10",
      "periodName": "October",
      "value": "27259",
      "footnotes": [
        {}
      ]
    },
    {
      "year": "2022",
      "period": "M09",
      "periodName": "September",
      "value": "26987",
      "footnotes": [
        {}
      ]
    },
    {
      "year": "2022",
      "period": "M08",
      "periodName": "August",
      "value": "25868",
      "footnotes": [
        {}
      ]
    },
    {
      "year": "2022",
      "period": "M07",
      "periodName": "July",
      "value": "25770",
      "footnotes": [
        {}
      ]
    },
    {
      "year": "2022",
      "period": "M06",
      "periodName": "June",
      "value": "25698",
      "footnotes": [
        {}
      ]
    },
    {
      "year": "2022",
      "period": "M05",
      "periodName": "May",
      "value": "26266",
      "footnotes": [
        {}
      ]
    },
    {
      "year": "2022",
      "period": "M04",
      "periodName": "April",
      "value": "26863",
      "footnotes": [
        {}
      ]
    },
    {
      "year": "2022",
      "period": "M03",
      "periodName": "March",
      "value": "26703",
      "footnotes": [
        {}
      ]
    },
    {
      "year": "2022",
      "period": "M02",
      "periodName": "February",
      "value": "26505",
      "footnotes": [
        {}
      ]
    },
    {
      "year": "2022",
      "period": "M01",
      "periodName": "January",
      "value": "25482",
      "footnotes": [
        {}
      ]
    },
    {
      "year": "2021",
      "period": "M12",
      "periodName": "December",
      "value": "26167",
      "footnotes": [
        {}
      ]
    },
    {
      "year": "2021",
      "period": "M11",
      "periodName": "November",
      "value": "26907",
      "footnotes": [
        {}
      ]
    },
    {
      "year": "2021",
      "period": "M10",
      "periodName": "October",
      "value": "26847",
      "footnotes": [
        {}
      ]
    },
    {
      "year": "2021",
      "period": "M09",
      "periodName": "September",
      "value": "26982",
      "footnotes": [
        {}
      ]
    },
    {
      "year": "2021",
      "period": "M08",
      "periodName": "August",
      "value": "25342",
      "footnotes": [
        {}
      ]
    },
    {
      "year": "2021",
      "period": "M07",
      "periodName": "July",
      "value": "24658",
      "footnotes": [
        {}
      ]
    },
    {
      "year": "2021",
      "period": "M06",
      "periodName": "June",
      "value": "24851",
      "footnotes": [
        {}
      ]
    },
    {
      "year": "2021",
      "period": "M05",
      "periodName": "May",
      "value": "25410",
      "footnotes": [
        {}
      ]
    },
    {
      "year": "2021",
      "period": "M04",
      "periodName": "April",
      "value": "25841",
      "footnotes": [
        {}
      ]
    },
    {
      "year": "2021",
      "period": "M03",
      "periodName": "March",
      "value": "25463",
      "footnotes": [
        {}
      ]
    },
    {
      "year": "2021",
      "period": "M02",
      "periodName": "February",
      "value": "25016",
      "footnotes": [
        {}
      ]
    },
    {
      "year": "2021",
      "period": "M01",
      "periodName": "January",
      "value": "24168",
      "footnotes": [
        {}
      ]
    }
  ]
}