{
  "seriesID": "LAUCN060250000000006",
  "data": [
    {
      "year": "2025",
      "period": "M12",
      "periodName": "December",
      "latest": "true",
      "value": "75238",
      "footnotes": [
        {
          "code": "P",
          "text": "Preliminary."
        }
      ]
    },
    {
      "year": "2025",
      "period": "M11",
      "periodName": "November",
      "value": "76619",
      "footnotes": [
        {}
      ]
    },
    {
      "year": "2025",
      "period": "M10",
      "periodName": "October",
      "value": "-",
      "footnotes": [
        {
          "code": "X",
          "text": "Data unavailable due to the 2025 lapse in appropriations."
        }
      ]
    },
    {
      "year": "2025",
      "period": "M09",
      "periodName": "September",
      "value": "77083",
      "footnotes": [
        {}
      ]
    },
    {
      "year": "2025",
      "period": "M08",
      "periodName": "August",
      "value": "76661",
      "footnotes": [
        {}
      ]
    },
    {
      "year": "2025",
      "period": "M07",
      "periodName": "July",
      "value": "73376",
      "footnotes": [
        {}
      ]
    },
    {
      "year": "2025",
      "period": "M06",
      "periodName": "June",
      "value": "74636",
      "footnotes": [
        {}
      ]
    },
    {
      "year": "2025",
      "period": "M05",
      "periodName": "May",
      "value": "74042",
      "footnotes": [
        {}
      ]
    },
    {
      "year": "2025",
      "period": "M04",
      "periodName": "April",
      "value": "71802",
      "footnotes": [
        {}
      ]
    },
    {
      "year": "2025",
      "period": "M03",
      "periodName": "March",
      "value": "73068",
      "footnotes": [
        {}
      ]
    },
    {
      "year": "2025",
      "period": "M02",
      "periodName": "February",
      "value": "73209",
      "footnotes": [
        {}
      ]
    },
    {
      "year": "2025",
      "period": "M01",
      "periodName": "January",
      "value": "73535",
      "footnotes": [
        {}
      ]
    },
    {
      "year": "2024",
      "period": "M12",
      "periodName": "December",
      "value": "73554",
      "footnotes": [
        {}
      ]
    },
    {
      "year": "2024",
      "period": "M11",
      "periodName": "November",
      "value": "74978",
      "footnotes": [
        {}
      ]
    },
    {
      "year": "2024",
      "period": "M10",
      "periodName": "October",
      "value": "74709",
      "footnotes": [
        {}
      ]
    },
    {
      "year": "2024",
      "period": "M09",
      "periodName": "September",
      "value": "74075",
      "footnotes": [
        {}
      ]
    },
    {
      "year": "2024",
      "period": "M08",
      "periodName": "August",
      "value": "74804",
      "footnotes": [
        {}
      ]
    },
    {
      "year": "2024",
      "period": "M07",
      "periodName": "July",
      "value": "72345",
      "footnotes": [
        {}
      ]
    },
    {
      "year": "2024",
      "period": "M06",
      "periodName": "June",
      "value": "72620",
      "footnotes": [
        {}
      ]
    },
    {
      "year": "2024",
      "period": "M05",
      "periodName": "May",
      "value": "71529",
      "footnotes": [
        {}
      ]
    },
    {
      "year": "2024",
      "period": "M04",
      "periodName": "April",
      "value": "70630",
      "footnotes": [
        {}
      ]
    },
    {
      "year": "2024",
      "period": "M03",
      "periodName": "March",
      "value": "71899",
      "footnotes": [
        {}
      ]
    },
    {
      "year": "2024",
      "period": "M02",
      "periodName": "February",
      "value": "72480",
      "footnotes": [
        {}
      ]
    },
    {
      "year": "2024",
      "period": "M01",
      "periodName": "January",
      "value": "72440",
      "footnotes": [
        {}
      ]
    },
    {
      "year": "2023",
      "period": "M12",
      "periodName": "December",
      "value": "72635",
      "footnotes": [
        {}
      ]
    },
    {
      "year": "2023",
      "period": "M11",
      "periodName": "November",
      "value": "73654",
      "footnotes": [
        {}
      ]
    },
    {
      "year": "2023",
      "period": "M10",
      "periodName": "October",
      "value": "74400",
      "footnotes": [
        {}
      ]
    },
    {
      "year": "2023",
      "period": "M09",
      "periodName": "September",
      "value": "73021",
      "footnotes": [
        {}
      ]
    },
    {
      "year": "2023",
      "period": "M08",
      "periodName": "August",
      "value": "73382",
      "footnotes": [
        {}
      ]
    },
    {
      "year": "2023",
      "period": "M07",
      "periodName": "July",
      "value": "70220",
      "footnotes": [
        {}
      ]
    },
    {
      "year": "2023",
      "period": "M06",
      "periodName": "June",
      "value": "71031",
      "footnotes": [
        {}
      ]
    },
    {
      "year": "2023",
      "period": "M05",
      "periodName": "May",
      "value": "70483",
      "footnotes": [
        {}
      ]
    },
    {
      "year": "2023",
      "period": "M04",
      "periodName": "April",
      "value": "68313",
      "footnotes": [
        {}
      ]
    },
    {
      "year": "2023",
      "period": "M03",
      "periodName": "March",
      "value": "70077",
      "footnotes": [
        {}
      ]
    },
    {
      "year": "2023",
      "period": "M02",
      "periodName": "February",
      "value": "69766",
      "footnotes": [
        {}
      ]
    },
    {
      "year": "2023",
      "period": "M01",
      "periodName": "January",
      "value": "70554",
      "footnotes": [
        {}
      ]
    },
    {
      "year": "2022",
      "period": "M12",
      "periodName": "December",
      "value": "69691",
      "footnotes": [
        {}
      ]
    },
    {
      "year": "2022",
      "period": "M11",
      "periodName": "November",
      "value": "70292",
      "footnotes": [
        {}
      ]
    },
    {
      "year": "2022",
      "period": "M10",
      "periodName": "October",
      "value": "70782",
      "footnotes": [
        {}
      ]
    },
    {
      "year": "2022",
      "period": "M09",
      "periodName": "September",
      "value": "69768",
      "footnotes": [
        {}
      ]
    },
    {
      "year": "2022",
      "period": "M08",
      "periodName": "August",
      "value": "69654",
      "footnotes": [
        {}
      ]
    },
    {
      "year": "2022",
      "period": "M07",
      "periodName": "July",
      "value": "66872",
      "footnotes": [
        {}
      ]
    },
    {
      "year": "2022",
      "period": "M06",
      "periodName": "June",
      "value": "67286",
      "footnotes": [
        {}
      ]
    },
    {
      "year": "2022",
      "period": "M05",
      "periodName": "May",
      "value": "66546",
      "footnotes": [
        {}
      ]
    },
    {
      "year": "2022",
      "period": "M04",
      "periodName": "April",
      "value": "65250",
      "footnotes": [
        {}
      ]
    },
    {
      "year": "2022",
      "period": "M03",
      "periodName": "March",
      "value": "66166",
      "footnotes": [
        {}
      ]
    },
    {
      "year": "2022",
      "period": "M02",
      "periodName": "February",
      "value": "67126",
      "footnotes": [
        {}
      ]
    },
    {
      "year": "2022",
      "period": "M01",
      "periodName": "January",
      "value": "67712",
      "footnotes": [
        {}
      ]
    },
    {
      "year": "2021",
      "period": "M12",
      "periodName": "December",
      "value": "66745",
      "footnotes": [
        {}
      ]
    },
    {
      "year": "2021",
      "period": "M11",
      "periodName": "November",
      "value": "67825",
      "footnotes": [
        {}
      ]
    },
    {
      "year": "2021",
      "period": "M10",
      "periodName": "October",
      "value": "68556",
      "footnotes": [
        {}
      ]
    },
    {
      "year": "2021",
      "period": "M09",
      "periodName": "September",
      "value": "67880",
      "footnotes": [
        {}
      ]
    },
    {
      "year": "2021",
      "period": "M08",
      "periodName": "August",
      "value": "67743",
      "footnotes": [
        {}
      ]
    },
    {
      "year": "2021",
      "period": "M07",
      "periodName": "July",
      "value": "66788",
      "footnotes": [
        {}
      ]
    },
    {
      "year": "2021",
      "period": "M06",
      "periodName": "June",
      "value": "68000",
      "footnotes": [
        {}
      ]
    },
    {
      "year": "2021",
      "period": "M05",
      "periodName": "May",
      "value": "66525",
      "footnotes": [
        {}
      ]
    },
    {
      "year": "2021",
      "period": "M04",
      "periodName": "April",
      "value": "65951",
      "footnotes": [
        {}
      ]
    },
    {
      "year": "2021",
      "period": "M03",
      "periodName": "March",
      "value": "66310",
      "footnotes": [
        {}
      ]
    },
    {
      "year": "2021",
      "period": "M02",
      "periodName": "February",
      "value": "66486",
      "footnotes": [
        {}
      ]
    },
    {
      "year": "2021",
      "period": "M01",
      "periodName": "January",
      "value": "66243",
      "footnotes": [
        {}
      ]
    }
  ]
}