{
  "seriesID": "LAUCN171190000000005",
  "data": [
    {
      "year": "2025",
      "period": "M12",
      "periodName": "December",
      "latest": "true",
      "value": "125020",
      "footnotes": [
        {
          "code": "P",
          "text": "Preliminary."
        }
      ]
    },
    {
      "year": "2025",
      "period": "M11",
      "periodName": "November",
      "value": "126374",
      "footnotes": [
        {}
      ]
    },
    {
      "year": "2025",
      "period": "M10",
      "periodName": "October",
      "value": "-",
      "footnotes": [
        {
          "code": "X",
          "text": "Data unavailable due to the 2025 lapse in appropriations."
        }
      ]
    },
    {
      "year": "2025",
      "period": "M09",
      "periodName": "September",
      "value": "126856",
      "footnotes": [
        {}
      ]
    },
    {
      "year": "2025",
      "period": "M08",
      "periodName": "August",
      "value": "126719",
      "footnotes": [
        {}
      ]
    },
    {
      "year": "2025",
      "period": "M07",
      "periodName": "July",
      "value": "130556",
      "footnotes": [
        {}
      ]
    },
    {
      "year": "2025",
      "period": "M06",
      "periodName": "June",
      "value": "131029",
      "footnotes": [
        {}
      ]
    },
    {
      "year": "2025",
      "period": "M05",
      "periodName": "May",
      "value": "129168",
      "footnotes": [
        {}
      ]
    },
    {
      "year": "2025",
      "period": "M04",
      "periodName": "April",
      "value": "130783",
      "footnotes": [
        {}
      ]
    },
    {
      "year": "2025",
      "period": "M03",
      "periodName": "March",
      "value": "128483",
      "footnotes": [
        {}
      ]
    },
    {
      "year": "2025",
      "period": "M02",
      "periodName": "February",
      "value": "127264",
      "footnotes": [
        {}
      ]
    },
    {
      "year": "2025",
      "period": "M01",
      "periodName": "January",
      "value": "127308",
      "footnotes": [
        {}
      ]
    },
    {
      "year": "2024",
      "period": "M12",
      "periodName": "December",
      "value": "130367",
      "footnotes": [
        {}
      ]
    },
    {
      "year": "2024",
      "period": "M11",
      "periodName": "November",
      "value": "129867",
      "footnotes": [
        {}
      ]
    },
    {
      "year": "2024",
      "period": "M10",
      "periodName": "October",
      "value": "130798",
      "footnotes": [
        {}
      ]
    },
    {
      "year": "2024",
      "period": "M09",
      "periodName": "September",
      "value": "130438",
      "footnotes": [
        {}
      ]
    },
    {
      "year": "2024",
      "period": "M08",
      "periodName": "August",
      "value": "129379",
      "footnotes": [
        {}
      ]
    },
    {
      "year": "2024",
      "period": "M07",
      "periodName": "July",
      "value": "131628",
      "footnotes": [
        {}
      ]
    },
    {
      "year": "2024",
      "period": "M06",
      "periodName": "June",
      "value": "131205",
      "footnotes": [
        {}
      ]
    },
    {
      "year": "2024",
      "period": "M05",
      "periodName": "May",
      "value": "130438",
      "footnotes": [
        {}
      ]
    },
    {
      "year": "2024",
      "period": "M04",
      "periodName": "April",
      "value": "129671",
      "footnotes": [
        {}
      ]
    },
    {
      "year": "2024",
      "period": "M03",
      "periodName": "March",
      "value": "129094",
      "footnotes": [
        {}
      ]
    },
    {
      "year": "2024",
      "period": "M02",
      "periodName": "February",
      "value": "128675",
      "footnotes": [
        {}
      ]
    },
    {
      "year": "2024",
      "period": "M01",
      "periodName": "January",
      "value": "128159",
      "footnotes": [
        {}
      ]
    },
    {
      "year": "2023",
      "period": "M12",
      "periodName": "December",
      "value": "129360",
      "footnotes": [
        {}
      ]
    },
    {
      "year": "2023",
      "period": "M11",
      "periodName": "November",
      "value": "130717",
      "footnotes": [
        {}
      ]
    },
    {
      "year": "2023",
      "period": "M10",
      "periodName": "October",
      "value": "130132",
      "footnotes": [
        {}
      ]
    },
    {
      "year": "2023",
      "period": "M09",
      "periodName": "September",
      "value": "129655",
      "footnotes": [
        {}
      ]
    },
    {
      "year": "2023",
      "period": "M08",
      "periodName": "August",
      "value": "129348",
      "footnotes": [
        {}
      ]
    },
    {
      "year": "2023",
      "period": "M07",
      "periodName": "July",
      "value": "129798",
      "footnotes": [
        {}
      ]
    },
    {
      "year": "2023",
      "period": "M06",
      "periodName": "June",
      "value": "128803",
      "footnotes": [
        {}
      ]
    },
    {
      "year": "2023",
      "period": "M05",
      "periodName": "May",
      "value": "128179",
      "footnotes": [
        {}
      ]
    },
    {
      "year": "2023",
      "period": "M04",
      "periodName": "April",
      "value": "128295",
      "footnotes": [
        {}
      ]
    },
    {
      "year": "2023",
      "period": "M03",
      "periodName": "March",
      "value": "127354",
      "footnotes": [
        {}
      ]
    },
    {
      "year": "2023",
      "period": "M02",
      "periodName": "February",
      "value": "126401",
      "footnotes": [
        {}
      ]
    },
    {
      "year": "2023",
      "period": "M01",
      "periodName": "January",
      "value": "125506",
      "footnotes": [
        {}
      ]
    },
    {
      "year": "2022",
      "period": "M12",
      "periodName": "December",
      "value": "127208",
      "footnotes": [
        {}
      ]
    },
    {
      "year": "2022",
      "period": "M11",
      "periodName": "November",
      "value": "126921",
      "footnotes": [
        {}
      ]
    },
    {
      "year": "2022",
      "period": "M10",
      "periodName": "October",
      "value": "126857",
      "footnotes": [
        {}
      ]
    },
    {
      "year": "2022",
      "period": "M09",
      "periodName": "September",
      "value": "127053",
      "footnotes": [
        {}
      ]
    },
    {
      "year": "2022",
      "period": "M08",
      "periodName": "August",
      "value": "127500",
      "footnotes": [
        {}
      ]
    },
    {
      "year": "2022",
      "period": "M07",
      "periodName": "July",
      "value": "129503",
      "footnotes": [
        {}
      ]
    },
    {
      "year": "2022",
      "period": "M06",
      "periodName": "June",
      "value": "128738",
      "footnotes": [
        {}
      ]
    },
    {
      "year": "2022",
      "period": "M05",
      "periodName": "May",
      "value": "127238",
      "footnotes": [
        {}
      ]
    },
    {
      "year": "2022",
      "period": "M04",
      "periodName": "April",
      "value": "126765",
      "footnotes": [
        {}
      ]
    },
    {
      "year": "2022",
      "period": "M03",
      "periodName": "March",
      "value": "127713",
      "footnotes": [
        {}
      ]
    },
    {
      "year": "2022",
      "period": "M02",
      "periodName": "February",
      "value": "126788",
      "footnotes": [
        {}
      ]
    },
    {
      "year": "2022",
      "period": "M01",
      "periodName": "January",
      "value": "126185",
      "footnotes": [
        {}
      ]
    },
    {
      "year": "2021",
      "period": "M12",
      "periodName": "December",
      "value": "127210",
      "footnotes": [
        {}
      ]
    },
    {
      "year": "2021",
      "period": "M11",
      "periodName": "November",
      "value": "128647",
      "footnotes": [
        {}
      ]
    },
    {
      "year": "2021",
      "period": "M10",
      "periodName": "October",
      "value": "126868",
      "footnotes": [
        {}
      ]
    },
    {
      "year": "2021",
      "period": "M09",
      "periodName": "September",
      "value": "127015",
      "footnotes": [
        {}
      ]
    },
    {
      "year": "2021",
      "period": "M08",
      "periodName": "August",
      "value": "125995",
      "footnotes": [
        {}
      ]
    },
    {
      "year": "2021",
      "period": "M07",
      "periodName": "July",
      "value": "127372",
      "footnotes": [
        {}
      ]
    },
    {
      "year": "2021",
      "period": "M06",
      "periodName": "June",
      "value": "127103",
      "footnotes": [
        {}
      ]
    },
    {
      "year": "2021",
      "period": "M05",
      "periodName": "May",
      "value": "126092",
      "footnotes": [
        {}
      ]
    },
    {
      "year": "2021",
      "period": "M04",
      "periodName": "April",
      "value": "126024",
      "footnotes": [
        {}
      ]
    },
    {
      "year": "2021",
      "period": "M03",
      "periodName": "March",
      "value": "125637",
      "footnotes": [
        {}
      ]
    },
    {
      "year": "2021",
      "period": "M02",
      "periodName": "February",
      "value": "125514",
      "footnotes": [
        {}
      ]
    },
    {
      "year": "2021",
      "period": "M01",
      "periodName": "January",
      "value": "125149",
      "footnotes": [
        {}
      ]
    }
  ]
}